papagai/__init__.py
papagai/__main__.py
papagai/cli.py
papagai/cmd.py
papagai/markdown.py
papagai/py.typed
papagai/worktree.py
papagai/primers/code.md
papagai/primers/review.md
papagai/tasks/c/floats-are-0.0.md
papagai/tasks/meson/meson.build-indentation-fixes.md
papagai/tasks/python/update-to-3.10.md
papagai/tasks/python/update-to-3.9.md
papagai-0.2.0.dist-info/METADATA
papagai-0.2.0.dist-info/WHEEL
papagai-0.2.0.dist-info/entry_points.txt
papagai-0.2.0.dist-info/RECORD
