Metadata-Version: 2.4
Name: papagai
Version: 0.2.0
Summary: A CLI tool to run Claude on git worktrees with automated commits
Project-URL: Homepage, https://github.com/whot/claude-instructions
Project-URL: Repository, https://github.com/whot/claude-instructions
Author-email: Peter Hutterer <peter.hutterer@who-t.net>
License: GPL-3.0-or-later
Classifier: Development Status :: 3 - Alpha
Classifier: Intended Audience :: Developers
Classifier: License :: OSI Approved :: GNU General Public License v3 or later (GPLv3+)
Classifier: Programming Language :: Python :: 3
Classifier: Programming Language :: Python :: 3.10
Classifier: Programming Language :: Python :: 3.11
Classifier: Programming Language :: Python :: 3.12
Classifier: Programming Language :: Python :: 3.13
Classifier: Topic :: Software Development :: Version Control :: Git
Requires-Python: >=3.10
Requires-Dist: click>=8.0
